wyoming_openai/__init__.py
wyoming_openai/__main__.py
wyoming_openai/compatibility.py
wyoming_openai/const.py
wyoming_openai/handler.py
wyoming_openai/utilities.py
wyoming_openai-0.4.0.dist-info/licenses/LICENSE
wyoming_openai-0.4.0.dist-info/METADATA
wyoming_openai-0.4.0.dist-info/WHEEL
wyoming_openai-0.4.0.dist-info/top_level.txt
wyoming_openai-0.4.0.dist-info/RECORD
