Metadata-Version: 2.4
Name: wyoming_openai
Version: 0.4.0
Summary: OpenAI-Compatible Proxy Middleware for the Wyoming Protocol
Author: Rory Eckel
License-Expression: Apache-2.0
Project-URL: Homepage, https://github.com/roryeckel/wyoming_openai
Project-URL: Issues, https://github.com/roryeckel/wyoming_openai/issues
Keywords: proxy,tts,openai,home-assistant,stt,asr,wyoming
Classifier: Intended Audience :: Developers
Classifier: Topic :: Multimedia :: Sound/Audio :: Speech
Classifier: Programming Language :: Python :: 3
Classifier: Programming Language :: Python :: 3.12
Classifier: Operating System :: OS Independent
Requires-Python: >=3.12
License-File: LICENSE
Requires-Dist: openai==2.15.0
Requires-Dist: wyoming==1.8.0
Requires-Dist: pysbd==0.3.4
Provides-Extra: dev
Requires-Dist: ruff==0.14.14; extra == "dev"
Requires-Dist: pytest==9.0.2; extra == "dev"
Requires-Dist: pytest-asyncio==1.3.0; extra == "dev"
Requires-Dist: pytest-mock==3.15.1; extra == "dev"
Requires-Dist: pytest-cov==7.0.0; extra == "dev"
Dynamic: license-file
